speech_user_interface/__init__.py
speech_user_interface/build_probabilities_for_speech.py
speech_user_interface/CommandArgs.py
speech_user_interface/CommandResults.py
speech_user_interface/compare_strings.py
speech_user_interface/CONSTANTS.py
speech_user_interface/download_file.py
speech_user_interface/load_vosk_model.py
speech_user_interface/move_directory_up_one_level.py
speech_user_interface/read_in_speech.py
speech_user_interface/send_text_to_chatgpt.py
speech_user_interface/speak_text.py
speech_user_interface/unzip_file.py
speech_user_interface-0.2.0.dist-info/entry_points.txt
speech_user_interface-0.2.0.dist-info/METADATA
speech_user_interface-0.2.0.dist-info/WHEEL
speech_user_interface-0.2.0.dist-info/RECORD
